{
  "orderId": 699688288641876861,
  "stage": "Decision Making",
  "model": "ChronosX-Ensemble-v1",
  "input": {
    "market": "BTC/USDT",
    "timeframe": "1m",
    "features": {
      "last_close": 87421.4,
      "sentiment_score": 0.40,
      "sentiment_confidence": 0.294,
      "volatility_regime": "neutral",
      "liquidity_24h_usdt": 4444445235
    },
    "risk_constraints": {
      "kelly_fraction": 0.25,
      "max_risk_per_trade": "2%",
      "circuit_breakers_active": false
    }
  },
  "output": {
    "decision": "OPEN_LONG",
    "confidence": 0.294,
    "position_size_btc": 0.0017,
    "entry_price": 87421.4,
    "execution_mode": "LIMIT"
  },
  "explanation": "ChronosX evaluated short-term market sentiment, volatility regime, and liquidity conditions. The ensemble produced a bullish signal with moderate confidence. Risk governance approved the trade after verifying Kelly sizing limits, leverage constraints, and circuit breaker conditions. A conservative position was executed to validate the AI signal under live market conditions."
}
